{
  "recommend": {
    "errorCode": 0,
    "banners": [
      {
        "id": 1975,
        "content": "探秘7女生集体跳楼自杀事件真相",
        "theme_id": 6624,
        "theme_info": {
          "id": 6624,
          "cover": "http://image.zhuizhuiimg.com//image/3973725_1506064522.jpg",
          "name": "探秘7女生集体跳楼自杀事件真相",
          "url": "zzComic://RC.com/43545",
          "comment_count": 0,
          "up_count": 0,
          "can_filter": 0
        }
      },
      {
        "id": 1983,
        "content": "暖心治愈又发人深省",
        "theme_id": 6632,
        "theme_info": {
          "id": 6632,
          "cover": "http://image.zhuizhuiimg.com//image/3978279_1506326926.jpg",
          "name": "暖心治愈又发人深省",
          "url": "http://aizhuizhui.com/new/58233",
          "comment_count": 0,
          "up_count": 0,
          "can_filter": 0
        }
      },
      {
        "id": 1984,
        "content": "Jump编辑长谈读者调查与腰斩；《狼的孩子雨和雪》漫画作者优因急性心脏衰竭阖然长逝",
        "theme_id": 6633,
        "theme_info": {
          "id": 6633,
          "cover": "http://image.zhuizhuiimg.com//image/3978419_1506335802.jpg",
          "name": "Jump编辑长谈读者调查与腰斩；《狼的孩子雨和雪》漫画作者优因急性心脏衰竭阖然长逝",
          "url": "http://aizhuizhui.com/new/58237",
          "comment_count": 0,
          "up_count": 0,
          "can_filter": 0
        }
      },
      {
        "id": 1708,
        "content": "【502】专栏 | 恍若历史 《惩役339年》",
        "theme_id": 6348,
        "theme_info": {
          "id": 6348,
          "cover": "http://image.zhuizhuiimg.com//image/3816513_1498468557.jpg",
          "name": "【502】专栏 | 恍若历史 《惩役339年》",
          "url": "http://aizhuizhui.com/new/49590",
          "comment_count": 0,
          "up_count": 0,
          "can_filter": 0
        }
      },
      {
        "id": 1982,
        "content": "【话题】说说最让你满意的长篇连载作品",
        "theme_id": 6631,
        "theme_info": {
          "id": 6631,
          "cover": "http://image.zhuizhuiimg.com//image/3978244_1506319682.jpg",
          "name": "【话题】说说最让你满意的长篇连载作品",
          "url": "http://aizhuizhui.com/new/57695",
          "comment_count": 0,
          "up_count": 0,
          "can_filter": 0
        }
      }
    ],
    "banner_ad_client_sdk_rank": [
      "5"
    ],
    "lists": [
      {
        "id": 66,
        "name": "爆笑到节操欠费",
        "content": "",
        "theme_id": 4620,
        "theme_info": {
          "id": 4620,
          "name": "节操可能已欠费",
          "url": "zzComic://L.CL.com/4620/S",
          "title": "节操可能已欠费",
          "comment_count": 0,
          "up_count": 0,
          "can_filter": 0
        },
        "comics": [
          {
            "id": 43530,
            "name": "造反俱乐部",
            "cover_img": "http://image.zhuizhuiimg.com//image/e02f1f53cfbcc7729bd5059417d89c7f.jpg",
            "finished": 0,
            "last_volume": "第37话",
            "topic_count": 17,
            "read_mode": 0,
            "have_resource": 1,
            "have_comic_review": 1,
            "comic_score": 8.8,
            "review_count": "6"
          },
          {
            "id": 43462,
            "name": "拉面加个蛋",
            "cover_img": "http://image.zhuizhuiimg.com//image/13e7fba2a34d00b71506184cc5e1680e.jpg",
            "finished": 0,
            "last_volume": "第12话 flag的力量",
            "topic_count": 3,
            "read_mode": 1,
            "have_resource": 1,
            "have_comic_review": 1,
            "comic_score": 8.4,
            "review_count": "3"
          },
          {
            "id": 43432,
            "name": "撩妹社",
            "cover_img": "http://image.zhuizhuiimg.com//image/3759038_1495684677.jpg",
            "finished": 0,
            "last_volume": "第二十七话",
            "topic_count": 34,
            "read_mode": 0,
            "have_resource": 1,
            "have_comic_review": 1,
            "comic_score": 5,
            "review_count": "46"
          },
          {
            "id": 40872,
            "name": "非人哉",
            "cover_img": "http://image.zhuizhuiimg.com//image/3400971_1479796303.jpg",
            "finished": 0,
            "last_volume": "272话",
            "topic_count": 2399,
            "read_mode": 1,
            "have_resource": 1,
            "have_comic_review": 1,
            "comic_score": 9.8,
            "review_count": "898"
          },
          {
            "id": 43476,
            "name": "QooApp：异常登入",
            "cover_img": "http://image.zhuizhuiimg.com//image/56ee616264b31b4a2b520317bdc01b0c.jpg",
            "finished": 0,
            "last_volume": "16 乱来的勇者大人",
            "topic_count": 7,
            "read_mode": 0,
            "have_resource": 1,
            "have_comic_review": 1,
            "comic_score": 7.9,
            "review_count": "1"
          },
          {
            "id": 43418,
            "name": "阿土博之节约集约用地",
            "cover_img": "http://image.zhuizhuiimg.com//image/132187b3aeebd612c75c2e0f318a8a6a.jpg",
            "finished": 0,
            "last_volume": "闲置的国有建设用地（二）",
            "topic_count": 1,
            "read_mode": 0,
            "have_resource": 1,
            "have_comic_review": 1,
            "comic_score": 6.5,
            "review_count": "2"
          }
        ],
        "obj_type": 2
      },
      {
        "id": 67,
        "name": "午后治愈茶果子",
        "content": "",
        "theme_id": 4621,
        "theme_info": {
          "id": 4621,
          "name": "午后治愈暖心",
          "url": "zzComic://L.CL.com/4621/S",
          "title": "午后治愈暖心",
          "comment_count": 0,
          "up_count": 0,
          "can_filter": 0
        },
        "comics": [
          {
            "id": 42817,
            "name": "夏洛特的道听途说",
            "cover_img": "http://image.zhuizhuiimg.com//image/3054616_1471331751.jpg",
            "finished": 0,
            "last_volume": "第38话",
            "topic_count": 111,
            "read_mode": 1,
            "have_resource": 1,
            "have_comic_review": 1,
            "comic_score": 8.8,
            "review_count": "32"
          },
          {
            "id": 41983,
            "name": "狗和猫的时间",
            "cover_img": "http://image.zhuizhuiimg.com//image/2144262_1461742980.jpg",
            "finished": 0,
            "last_volume": "75话",
            "topic_count": 65,
            "read_mode": 0,
            "have_resource": 1,
            "have_comic_review": 1,
            "comic_score": 8.9,
            "review_count": "30"
          },
          {
            "id": 40838,
            "name": "辛巴狗和哈米兔",
            "cover_img": "http://image.zhuizhuiimg.com//image/1024377_1449808184.jpg",
            "finished": 0,
            "last_volume": "第62话",
            "topic_count": 7,
            "read_mode": 0,
            "have_resource": 1,
            "have_comic_review": 1,
            "comic_score": 8.3,
            "review_count": "14"
          },
          {
            "id": 41582,
            "name": "怕丢日记",
            "cover_img": "http://image.zhuizhuiimg.com//image/1792201_1457686167.jpg",
            "finished": 0,
            "last_volume": "46话",
            "topic_count": 335,
            "read_mode": 1,
            "have_resource": 1,
            "have_comic_review": 1,
            "comic_score": 9.5,
            "review_count": "201"
          },
          {
            "id": 43524,
            "name": "亡者的眼药",
            "cover_img": "http://image.zhuizhuiimg.com//image/66998d3865ed81319e702b841598c74f.jpg",
            "finished": 1,
            "last_volume": "全1话",
            "topic_count": 13,
            "read_mode": 0,
            "have_resource": 1,
            "have_comic_review": 1,
            "comic_score": 8.4,
            "review_count": "12"
          },
          {
            "id": 41858,
            "name": "千夏的森林",
            "cover_img": "http://image.zhuizhuiimg.com//image/2046499_1460550711.jpg",
            "finished": 0,
            "last_volume": "14话",
            "topic_count": 102,
            "read_mode": 0,
            "have_resource": 1,
            "have_comic_review": 1,
            "comic_score": 8.7,
            "review_count": "61"
          }
        ],
        "obj_type": 2
      },
      {
        "id": 68,
        "name": "古风佳人曲难留",
        "content": "",
        "theme_id": 4617,
        "theme_info": {
          "id": 4617,
          "name": "古风佳人",
          "url": "zzComic://L.CL.com/4617/S",
          "title": "古风佳人",
          "comment_count": 0,
          "up_count": 0,
          "can_filter": 0
        },
        "comics": [
          {
            "id": 43420,
            "name": "黄雀传",
            "cover_img": "http://image.zhuizhuiimg.com//image/e996444a4972c89c25392880e0b17cf9.jpg",
            "finished": 0,
            "last_volume": "休更声明",
            "topic_count": 660,
            "read_mode": 0,
            "have_resource": 1,
            "have_comic_review": 1,
            "comic_score": 19.4,
            "review_count": "288"
          },
          {
            "id": 43514,
            "name": "茶壶里的仙儿",
            "cover_img": "http://image.zhuizhuiimg.com//image/00c2eeb207fc7720199ef535f36e03c0.jpg",
            "finished": 1,
            "last_volume": "下",
            "topic_count": 3,
            "read_mode": 0,
            "have_resource": 1,
            "have_comic_review": 1,
            "comic_score": 9.2,
            "review_count": "1"
          },
          {
            "id": 42843,
            "name": "神明",
            "cover_img": "http://image.zhuizhuiimg.com//image/9d87aba88124a183aee1b8d9ed52f066.jpg",
            "finished": 0,
            "last_volume": "第二十四章魇兽现身",
            "topic_count": 16,
            "read_mode": 0,
            "have_resource": 1,
            "have_comic_review": 1,
            "comic_score": 7,
            "review_count": "21"
          },
          {
            "id": 43431,
            "name": "钟馗传",
            "cover_img": "http://image.zhuizhuiimg.com//image/3757124_1495541784.jpg",
            "finished": 0,
            "last_volume": "91上",
            "topic_count": 27,
            "read_mode": 0,
            "have_resource": 1,
            "have_comic_review": 1,
            "comic_score": 8.9,
            "review_count": "6"
          },
          {
            "id": 43412,
            "name": "神之眧",
            "cover_img": "http://image.zhuizhuiimg.com//image/f30735a737bddb7f78e84d732fd3daba.jpg",
            "finished": 0,
            "last_volume": "第14话",
            "topic_count": 62,
            "read_mode": 1,
            "have_resource": 1,
            "have_comic_review": 1,
            "comic_score": 9.3,
            "review_count": "38"
          },
          {
            "id": 43398,
            "name": "龙符之王道天下",
            "cover_img": "http://image.zhuizhuiimg.com//image/7798adfb3c2a2fbcfca74b653e9b0e7b.jpg",
            "finished": 0,
            "last_volume": "第75话 南蛮魔族 01",
            "topic_count": 56,
            "read_mode": 0,
            "have_resource": 1,
            "have_comic_review": 1,
            "comic_score": 8.8,
            "review_count": "37"
          }
        ],
        "obj_type": 2
      },
      {
        "id": 59,
        "name": "每日上榜热门小组",
        "content": "每日上榜热门小组",
        "theme_id": 3900,
        "theme_info": {
          "id": 3900,
          "name": "追追同好会",
          "url": "zzComic://L.TL.com/3900",
          "comment_count": 0,
          "up_count": 0,
          "can_filter": 0
        },
        "theme_list": [
          {
            "id": 3893,
            "cover": "http://image.zhuizhuiimg.com//image/1242121_1452334114.jpg",
            "name": "耽美小组",
            "url": "zzcomic://g.com/4",
            "comment_count": 0,
            "up_count": 0,
            "can_filter": 0
          },
          {
            "id": 4267,
            "cover": "http://image.zhuizhuiimg.com//image/1221623_1452079601.jpg",
            "name": "刀剑乱舞小组",
            "url": "zzcomic://g.com/13",
            "comment_count": 0,
            "up_count": 0,
            "can_filter": 0
          },
          {
            "id": 4623,
            "cover": "http://image.zhuizhuiimg.com//image/1748120_1457148668.jpg",
            "name": "百合小组",
            "url": "zzcomic://g.com/17",
            "comment_count": 0,
            "up_count": 0,
            "can_filter": 0
          },
          {
            "id": 5100,
            "cover": "http://image.zhuizhuiimg.com//image/2627153_1467377377.jpg",
            "name": "小说小组",
            "url": "zzcomic://g.com/24",
            "comment_count": 0,
            "up_count": 0,
            "can_filter": 0
          }
        ],
        "obj_type": 1
      },
      {
        "id": 64,
        "name": "热血漫小宇宙",
        "content": "",
        "theme_id": 4618,
        "theme_info": {
          "id": 4618,
          "name": "热血漫小宇宙",
          "url": "zzComic://L.CL.com/4618/S",
          "title": "热血漫小宇宙",
          "comment_count": 0,
          "up_count": 0,
          "can_filter": 0
        },
        "comics": [
          {
            "id": 42132,
            "name": "驭灵师",
            "cover_img": "http://image.zhuizhuiimg.com//image/3782261_1496816326.jpg",
            "finished": 0,
            "last_volume": "149话",
            "topic_count": 758,
            "read_mode": 0,
            "have_resource": 1,
            "have_comic_review": 1,
            "comic_score": 9.5,
            "review_count": "308"
          },
          {
            "id": 41252,
            "name": "百炼成神",
            "cover_img": "http://image.zhuizhuiimg.com//image/3614270_1488260935.jpg",
            "finished": 0,
            "last_volume": "第144话 炼体机缘",
            "topic_count": 680,
            "read_mode": 0,
            "have_resource": 1,
            "have_comic_review": 1,
            "comic_score": 9.3,
            "review_count": "265"
          },
          {
            "id": 43502,
            "name": "光影对决",
            "cover_img": "http://image.zhuizhuiimg.com//image/32865e4782fab0929ed9e1461c5882a1.jpg",
            "finished": 0,
            "last_volume": "第14话",
            "topic_count": 10,
            "read_mode": 0,
            "have_resource": 1,
            "have_comic_review": 1,
            "comic_score": 8.5,
            "review_count": "1"
          },
          {
            "id": 42812,
            "name": "天梯劝降学园",
            "cover_img": "http://image.zhuizhuiimg.com//image/63a5c8e5e22ecdb518dd8fdc4ee24d93.jpg",
            "finished": 0,
            "last_volume": "第20话D",
            "topic_count": 103,
            "read_mode": 0,
            "have_resource": 1,
            "have_comic_review": 1,
            "comic_score": 8.3,
            "review_count": "48"
          },
          {
            "id": 43498,
            "name": "无形门之幽州谍影",
            "cover_img": "http://image.zhuizhuiimg.com//image/cf9762cc9d078784aabd03f9571714b1.jpg",
            "finished": 0,
            "last_volume": "第29回",
            "topic_count": 15,
            "read_mode": 0,
            "have_resource": 1,
            "have_comic_review": 1,
            "comic_score": 8.9,
            "review_count": "1"
          },
          {
            "id": 43532,
            "name": "天空之魂",
            "cover_img": "http://image.zhuizhuiimg.com//image/671e00c9d2015dc95a286fb1cdb90b3a.jpg",
            "finished": 0,
            "last_volume": "战斗前夕-I",
            "topic_count": 3,
            "read_mode": 0,
            "have_resource": 1,
            "have_comic_review": 1,
            "comic_score": 7.5,
            "review_count": "5"
          }
        ],
        "obj_type": 2
      },
      {
        "id": 72,
        "name": "耽美那些事儿",
        "content": "",
        "theme_id": 4855,
        "theme_info": {
          "id": 4855,
          "name": "耽美那些事儿",
          "url": "zzComic://G.CL.com/4855/S",
          "title": "耽美那些事儿",
          "comment_count": 0,
          "up_count": 0,
          "can_filter": 0
        },
        "comics": [
          {
            "id": 43505,
            "name": "Ring A Bell",
            "cover_img": "http://image.zhuizhuiimg.com//image/2bfd336568c8b9b41dc7dc8c095be370.jpg",
            "finished": 0,
            "last_volume": "7话",
            "topic_count": 18,
            "read_mode": 0,
            "have_resource": 1,
            "have_comic_review": 1,
            "comic_score": 8.3,
            "review_count": "12"
          },
          {
            "id": 43259,
            "name": "与妖成萌",
            "cover_img": "http://image.zhuizhuiimg.com//image/c2ab2b61cf67376e9e5c51dbd51e2d55.jpg",
            "finished": 0,
            "last_volume": "第二十一话·引血为契·下",
            "topic_count": 87,
            "read_mode": 0,
            "have_resource": 1,
            "have_comic_review": 1,
            "comic_score": 9.1,
            "review_count": "54"
          },
          {
            "id": 43284,
            "name": "麒麟骨",
            "cover_img": "http://image.zhuizhuiimg.com//image/0da27ce0db477aa39a9054005b746e09.jpg",
            "finished": 0,
            "last_volume": "鞭打韩大人",
            "topic_count": 102,
            "read_mode": 0,
            "have_resource": 1,
            "have_comic_review": 1,
            "comic_score": 9.1,
            "review_count": "37"
          },
          {
            "id": 43260,
            "name": "我的室友好奇怪",
            "cover_img": "http://image.zhuizhuiimg.com//image/d0a5b88b0b2833e6a65cb195d521a17e.jpg",
            "finished": 0,
            "last_volume": "第47话（完结篇）",
            "topic_count": 119,
            "read_mode": 1,
            "have_resource": 1,
            "have_comic_review": 1,
            "comic_score": 9,
            "review_count": "133"
          },
          {
            "id": 43504,
            "name": "惊天动地",
            "cover_img": "http://image.zhuizhuiimg.com//image/39820e9d3d8f76943ee531c45c450756.jpg",
            "finished": 0,
            "last_volume": "7话",
            "topic_count": 21,
            "read_mode": 0,
            "have_resource": 1,
            "have_comic_review": 1,
            "comic_score": 8.7,
            "review_count": "28"
          },
          {
            "id": 43530,
            "name": "造反俱乐部",
            "cover_img": "http://image.zhuizhuiimg.com//image/e02f1f53cfbcc7729bd5059417d89c7f.jpg",
            "finished": 0,
            "last_volume": "第37话",
            "topic_count": 17,
            "read_mode": 0,
            "have_resource": 1,
            "have_comic_review": 1,
            "comic_score": 8.8,
            "review_count": "6"
          }
        ],
        "obj_type": 2
      },
      {
        "id": 57,
        "name": "追追每日漫评精选",
        "content": "",
        "theme_list": [
          {
            "id": 6632,
            "cover": "http://image.zhuizhuiimg.com//image/3978279_1506326926.jpg",
            "name": "暖心治愈又发人深省",
            "url": "http://aizhuizhui.com/new/58233",
            "comment_count": 0,
            "up_count": 0,
            "can_filter": 0
          },
          {
            "id": 3145,
            "cover": "http://image.zhuizhuiimg.com//image/1159295_1451382434.jpg",
            "name": "每日漫评精选",
            "url": "zzComic://L.TL.com/3145",
            "comment_count": 0,
            "up_count": 0,
            "can_filter": 0
          }
        ],
        "obj_type": 1
      },
      {
        "id": 53,
        "name": "黑白漫文化专栏",
        "content": "黑白漫文化专栏",
        "theme_list": [
          {
            "id": 6348,
            "cover": "http://image.zhuizhuiimg.com//image/3816513_1498468557.jpg",
            "name": "【502】专栏 | 恍若历史 《惩役339年》",
            "url": "http://aizhuizhui.com/new/49590",
            "comment_count": 0,
            "up_count": 0,
            "can_filter": 0
          },
          {
            "id": 2927,
            "cover": "http://image.zhuizhuiimg.com//image/1159312_1451382612.jpg",
            "name": "黑白漫文化",
            "url": "http://aizhuizhui.com/new_culture",
            "comment_count": 0,
            "up_count": 0,
            "can_filter": 0
          }
        ],
        "obj_type": 1
      },
      {
        "id": 70,
        "name": "悬疑诡计夜未眠",
        "content": "悬疑诡计夜未眠",
        "theme_id": 4660,
        "theme_info": {
          "id": 4660,
          "name": "悬疑诡计夜未眠",
          "url": "zzComic://L.CL.com/4660/S",
          "title": "悬疑诡计夜未眠",
          "comment_count": 0,
          "up_count": 0,
          "can_filter": 0
        },
        "comics": [
          {
            "id": 43397,
            "name": "这个QQ群绝逼有毒",
            "cover_img": "http://image.zhuizhuiimg.com//image/832beeed5216ef67395e3b4e92af3e19.jpg",
            "finished": 0,
            "last_volume": "32话",
            "topic_count": 51,
            "read_mode": 0,
            "have_resource": 1,
            "have_comic_review": 1,
            "comic_score": 7.7,
            "review_count": "31"
          },
          {
            "id": 43545,
            "name": "人间志异录",
            "cover_img": "http://image.zhuizhuiimg.com//image/3942579_1504072102.jpg",
            "finished": 0,
            "last_volume": "第4话（下）",
            "topic_count": 19,
            "read_mode": 1,
            "have_resource": 1,
            "have_comic_review": 1,
            "comic_score": 11.2,
            "review_count": "13"
          },
          {
            "id": 43401,
            "name": "中国异闻录",
            "cover_img": "http://image.zhuizhuiimg.com//image/640270f28d611ba43e4a346cf02c5e35.jpg",
            "finished": 0,
            "last_volume": "红油伞四",
            "topic_count": 12,
            "read_mode": 0,
            "have_resource": 1,
            "have_comic_review": 1,
            "comic_score": 8.5,
            "review_count": "6"
          },
          {
            "id": 43511,
            "name": "阴眸诡记",
            "cover_img": "http://image.zhuizhuiimg.com//image/3857867_1500445417.jpg",
            "finished": 0,
            "last_volume": "12 反邪教局的介入",
            "topic_count": 20,
            "read_mode": 0,
            "have_resource": 1,
            "have_comic_review": 1,
            "comic_score": 8.3,
            "review_count": "13"
          },
          {
            "id": 43495,
            "name": "夜伴尖叫",
            "cover_img": "http://image.zhuizhuiimg.com//image/883a3212d4fd576128699305e45630c2.jpg",
            "finished": 0,
            "last_volume": "第7话A",
            "topic_count": 11,
            "read_mode": 1,
            "have_resource": 1,
            "have_comic_review": 1,
            "comic_score": 8.2,
            "review_count": "13"
          },
          {
            "id": 43451,
            "name": "欲望之扉",
            "cover_img": "http://image.zhuizhuiimg.com//image/d5e5aeae50c5a5c640777b3c2d2bb850.jpg",
            "finished": 0,
            "last_volume": "第20话",
            "topic_count": 45,
            "read_mode": 0,
            "have_resource": 1,
            "have_comic_review": 1,
            "comic_score": 8.3,
            "review_count": "17"
          }
        ],
        "obj_type": 2
      },
      {
        "id": 75,
        "name": "轻松Q版小日常",
        "content": "",
        "theme_id": 4891,
        "theme_info": {
          "id": 4891,
          "name": "轻松Q版小日常",
          "url": "zzComic://L.CL.com/4891/S",
          "title": "轻松日常小四格",
          "comment_count": 0,
          "up_count": 0,
          "can_filter": 0
        },
        "comics": [
          {
            "id": 43278,
            "name": "大清第一男秘",
            "cover_img": "http://image.zhuizhuiimg.com//image/b0493746245ad7605584c412fd2bfe27.jpg",
            "finished": 0,
            "last_volume": "一方霸犬",
            "topic_count": 12,
            "read_mode": 1,
            "have_resource": 1,
            "have_comic_review": 1,
            "comic_score": 8.9,
            "review_count": "9"
          },
          {
            "id": 41490,
            "name": "武林萌主",
            "cover_img": "http://image.zhuizhuiimg.com//image/1723378_1456829922.jpg",
            "finished": 0,
            "last_volume": "1话",
            "topic_count": 35,
            "read_mode": 0,
            "have_resource": 1,
            "have_comic_review": 1,
            "comic_score": 8.8,
            "review_count": "34"
          },
          {
            "id": 40615,
            "name": "诶？捡到一个小僵尸",
            "cover_img": "http://image.zhuizhuiimg.com//image/872485_1447732900.jpg",
            "finished": 0,
            "last_volume": "82话",
            "topic_count": 617,
            "read_mode": 0,
            "have_resource": 1,
            "have_comic_review": 1,
            "comic_score": 9.6,
            "review_count": "729"
          },
          {
            "id": 42091,
            "name": "吸血高中生血饺哥",
            "cover_img": "http://image.zhuizhuiimg.com//image/2235356_1462789706.jpg",
            "finished": 0,
            "last_volume": "337话",
            "topic_count": 781,
            "read_mode": 1,
            "have_resource": 1,
            "have_comic_review": 1,
            "comic_score": 9.5,
            "review_count": "233"
          },
          {
            "id": 43537,
            "name": "轻松家",
            "cover_img": "http://image.zhuizhuiimg.com//image/d4e9ae7705b4a2ee5be71ca01f4d5c34.jpg",
            "finished": 0,
            "last_volume": "你在看什么",
            "topic_count": 0,
            "read_mode": 1,
            "have_resource": 1,
            "have_comic_review": 1,
            "comic_score": 7.4,
            "review_count": "1"
          },
          {
            "id": 40838,
            "name": "辛巴狗和哈米兔",
            "cover_img": "http://image.zhuizhuiimg.com//image/1024377_1449808184.jpg",
            "finished": 0,
            "last_volume": "第62话",
            "topic_count": 7,
            "read_mode": 0,
            "have_resource": 1,
            "have_comic_review": 1,
            "comic_score": 8.3,
            "review_count": "14"
          }
        ],
        "obj_type": 2
      },
      {
        "id": 18,
        "name": "热门话题讨论区",
        "content": "",
        "theme_list": [
          {
            "id": 6631,
            "cover": "http://image.zhuizhuiimg.com//image/3978244_1506319682.jpg",
            "name": "【话题】说说最让你满意的长篇连载作品",
            "url": "http://aizhuizhui.com/new/57695",
            "comment_count": 0,
            "up_count": 0,
            "can_filter": 0
          },
          {
            "id": 2995,
            "cover": "http://image.zhuizhuiimg.com//image/538819_1443081544.jpg",
            "name": "话题",
            "url": "http://aizhuizhui.com/new_huati",
            "comment_count": 0,
            "up_count": 0,
            "can_filter": 0
          }
        ],
        "obj_type": 1
      },
      {
        "id": 65,
        "name": "少女心砰砰砰",
        "content": "",
        "theme_id": 4619,
        "theme_info": {
          "id": 4619,
          "name": "少女心砰砰砰",
          "url": "zzComic://L.CL.com/4619/S",
          "title": "少女心砰砰砰",
          "comment_count": 0,
          "up_count": 0,
          "can_filter": 0
        },
        "comics": [
          {
            "id": 43460,
            "name": "甜心教练",
            "cover_img": "http://image.zhuizhuiimg.com//image/129e8092d3f6f3fe87b6ad0a5bc0b39d.jpg",
            "finished": 0,
            "last_volume": "君夜与凌炫的对决",
            "topic_count": 35,
            "read_mode": 1,
            "have_resource": 1,
            "have_comic_review": 1,
            "comic_score": 9.1,
            "review_count": "46"
          },
          {
            "id": 43393,
            "name": "非量产型穿越",
            "cover_img": "http://image.zhuizhuiimg.com//image/c1c1b2cbd961fc7a099810f20da64b62.jpg",
            "finished": 0,
            "last_volume": "第57话",
            "topic_count": 153,
            "read_mode": 0,
            "have_resource": 1,
            "have_comic_review": 1,
            "comic_score": 9.8,
            "review_count": "58"
          },
          {
            "id": 43549,
            "name": "王爷你好坏",
            "cover_img": "http://image.zhuizhuiimg.com//image/41d7781169ef185c6e98839cb6c60cc4.jpg",
            "finished": 0,
            "last_volume": "第5话",
            "topic_count": 8,
            "read_mode": 1,
            "have_resource": 1,
            "have_comic_review": 1,
            "comic_score": 9,
            "review_count": "7"
          },
          {
            "id": 43522,
            "name": "忘川",
            "cover_img": "http://image.zhuizhuiimg.com//image/3b55148528dc79c437ee8cc42c4e9145.jpg",
            "finished": 1,
            "last_volume": "下篇",
            "topic_count": 20,
            "read_mode": 0,
            "have_resource": 1,
            "have_comic_review": 1,
            "comic_score": 9.1,
            "review_count": "24"
          },
          {
            "id": 43523,
            "name": "狐伶寺",
            "cover_img": "http://image.zhuizhuiimg.com//image/196f89d974da6304c05be901c287e557.jpg",
            "finished": 1,
            "last_volume": "下",
            "topic_count": 2,
            "read_mode": 0,
            "have_resource": 1,
            "have_comic_review": 1,
            "comic_score": 9.1,
            "review_count": "11"
          },
          {
            "id": 43324,
            "name": "我是高富帅",
            "cover_img": "http://image.zhuizhuiimg.com//image/e899d1caaeb1a06549435a6fc8926b59.jpg",
            "finished": 0,
            "last_volume": "第四十一话",
            "topic_count": 46,
            "read_mode": 1,
            "have_resource": 1,
            "have_comic_review": 1,
            "comic_score": 8.4,
            "review_count": "34"
          }
        ],
        "obj_type": 2
      },
      {
        "id": 71,
        "name": "科幻宇宙大爆炸",
        "content": "科幻宇宙大爆炸",
        "theme_id": 4803,
        "theme_info": {
          "id": 4803,
          "name": "科幻宇宙大爆炸",
          "url": "zzComic://L.CL.com/4803/S",
          "title": "科幻宇宙大爆炸",
          "comment_count": 0,
          "up_count": 0,
          "can_filter": 0
        },
        "comics": [
          {
            "id": 43476,
            "name": "QooApp：异常登入",
            "cover_img": "http://image.zhuizhuiimg.com//image/56ee616264b31b4a2b520317bdc01b0c.jpg",
            "finished": 0,
            "last_volume": "16 乱来的勇者大人",
            "topic_count": 7,
            "read_mode": 0,
            "have_resource": 1,
            "have_comic_review": 1,
            "comic_score": 7.9,
            "review_count": "1"
          },
          {
            "id": 43039,
            "name": "微能力者",
            "cover_img": "http://image.zhuizhuiimg.com//image/3217912_1474280615.jpg",
            "finished": 0,
            "last_volume": "第69话 失控",
            "topic_count": 80,
            "read_mode": 1,
            "have_resource": 1,
            "have_comic_review": 1,
            "comic_score": 8.7,
            "review_count": "42"
          },
          {
            "id": 43527,
            "name": "魔星双龙传",
            "cover_img": "http://image.zhuizhuiimg.com//image/b5fa4ee8bcf37b7b3411ca2d813849c1.jpg",
            "finished": 0,
            "last_volume": "第12话 下 鬼虎牌“祛屎灵”",
            "topic_count": 13,
            "read_mode": 0,
            "have_resource": 1,
            "have_comic_review": 1,
            "comic_score": 7.1,
            "review_count": "2"
          },
          {
            "id": 43532,
            "name": "天空之魂",
            "cover_img": "http://image.zhuizhuiimg.com//image/671e00c9d2015dc95a286fb1cdb90b3a.jpg",
            "finished": 0,
            "last_volume": "战斗前夕-I",
            "topic_count": 3,
            "read_mode": 0,
            "have_resource": 1,
            "have_comic_review": 1,
            "comic_score": 7.5,
            "review_count": "5"
          },
          {
            "id": 43538,
            "name": "穿越效应",
            "cover_img": "http://image.zhuizhuiimg.com//image/289505b0cbc090177099f6685941c981.jpg",
            "finished": 0,
            "last_volume": "第三章 圣武密训（2）",
            "topic_count": 8,
            "read_mode": 0,
            "have_resource": 1,
            "have_comic_review": 1,
            "comic_score": 8.6,
            "review_count": "4"
          },
          {
            "id": 43513,
            "name": "晴空城",
            "cover_img": "http://image.zhuizhuiimg.com//image/e3a63601a70949e3454c84c463aa8d3e.jpg",
            "finished": 0,
            "last_volume": "第3话 赏金猎人（上）",
            "topic_count": 6,
            "read_mode": 0,
            "have_resource": 1,
            "have_comic_review": 1,
            "comic_score": 8.7,
            "review_count": "6"
          }
        ],
        "obj_type": 2
      },
      {
        "id": 73,
        "name": "暴走大事件",
        "content": "暴走大事件",
        "theme_list": [
          {
            "id": 6621,
            "cover": "http://image.zhuizhuiimg.com//image/3973525_1506047243.jpg",
            "name": "【暴走大事件第五季】32 纸巾化身中国版教父分分钟主持公道",
            "url": "http://aizhuizhui.com/new/video/57910",
            "comment_count": 0,
            "up_count": 0,
            "can_filter": 0
          },
          {
            "id": 4962,
            "cover": "http://image.zhuizhuiimg.com//image/2406327_1464939388.jpg",
            "name": "暴走大事件往期回顾",
            "url": "http://aizhuizhui.com/bz_video",
            "comment_count": 0,
            "up_count": 0,
            "can_filter": 0
          }
        ],
        "obj_type": 1
      },
      {
        "id": 74,
        "name": "游戏改编漫画",
        "content": "",
        "theme_id": 4885,
        "theme_info": {
          "id": 4885,
          "name": "游戏改编漫画",
          "url": "zzComic://L.CL.com/4885/S",
          "title": "游戏改编漫画",
          "comment_count": 0,
          "up_count": 0,
          "can_filter": 0
        },
        "comics": [
          {
            "id": 41981,
            "name": "19 GOLD LOL",
            "cover_img": "http://image.zhuizhuiimg.com//image/2144252_1461742536.jpg",
            "finished": 0,
            "last_volume": "23话（完结）",
            "topic_count": 109,
            "read_mode": 1,
            "have_resource": 1,
            "have_comic_review": 1,
            "comic_score": 9.6,
            "review_count": "25"
          },
          {
            "id": 41798,
            "name": "英雄联盟-欢快下路",
            "cover_img": "http://image.zhuizhuiimg.com//image/2000483_1460028492.jpg",
            "finished": 0,
            "last_volume": "索拉卡",
            "topic_count": 6,
            "read_mode": 0,
            "have_resource": 1,
            "have_comic_review": 1,
            "comic_score": 9.7,
            "review_count": "4"
          },
          {
            "id": 43536,
            "name": "恒水中学连环虐杀事件",
            "cover_img": "http://image.zhuizhuiimg.com//image/241c99618968d9b7e3e920203fb21168.jpg",
            "finished": 1,
            "last_volume": "26话",
            "topic_count": 14,
            "read_mode": 0,
            "have_resource": 1,
            "have_comic_review": 1,
            "comic_score": 7,
            "review_count": "3"
          },
          {
            "id": 42122,
            "name": "造物法则",
            "cover_img": "http://image.zhuizhuiimg.com//image/4961aea022a25b8fdd1d732183c3d7e6.jpg",
            "finished": 0,
            "last_volume": "第118话：痛苦的根源",
            "topic_count": 121,
            "read_mode": 0,
            "have_resource": 1,
            "have_comic_review": 1,
            "comic_score": 8.8,
            "review_count": "150"
          },
          {
            "id": 41982,
            "name": "疯癫LOL",
            "cover_img": "http://image.zhuizhuiimg.com//image/2144257_1461742782.jpg",
            "finished": 0,
            "last_volume": "72话",
            "topic_count": 102,
            "read_mode": 1,
            "have_resource": 1,
            "have_comic_review": 1,
            "comic_score": 9.1,
            "review_count": "30"
          },
          {
            "id": 42763,
            "name": "乱七八糟的妖刀少女",
            "cover_img": "http://image.zhuizhuiimg.com//image/3107779_1471922787.jpg",
            "finished": 0,
            "last_volume": "16话",
            "topic_count": 9,
            "read_mode": 0,
            "have_resource": 1,
            "have_comic_review": 1,
            "comic_score": 7.5,
            "review_count": "9"
          }
        ],
        "obj_type": 2
      },
      {
        "id": 58,
        "name": "官方给坑同人来填",
        "content": "官方给坑同人来填",
        "theme_id": 3720,
        "theme_info": {
          "id": 3720,
          "name": "官方给坑同人来填",
          "url": "zzComic://L.CL.com/3720/S",
          "title": "官方给坑同人来填",
          "comment_count": 0,
          "up_count": 0,
          "can_filter": 0
        },
        "comics": [
          {
            "id": 39697,
            "name": "盗墓笔记同人专区",
            "cover_img": "http://image.zhuizhuiimg.com//image/1150274_1451269793.jpg",
            "finished": 0,
            "last_volume": "(瓶邪)深渊06byK猫",
            "topic_count": 1206,
            "read_mode": 1,
            "have_resource": 1,
            "have_comic_review": 1,
            "comic_score": 9.5,
            "review_count": "290"
          },
          {
            "id": 40716,
            "name": "全职高手同人专区",
            "cover_img": "http://image.zhuizhuiimg.com//image/915598_1448364921.jpg",
            "finished": 0,
            "last_volume": "全明星新人VS老鸟的另一番风味by团表哥",
            "topic_count": 339,
            "read_mode": 1,
            "have_resource": 1,
            "have_comic_review": 1,
            "comic_score": 9.5,
            "review_count": "161"
          },
          {
            "id": 39652,
            "name": "刀剑乱舞同人专区",
            "cover_img": "http://image.zhuizhuiimg.com//image/3159668_1472815504.jpg",
            "finished": 0,
            "last_volume": "包丁人妻的话题by小哈哈Vovo2000",
            "topic_count": 1266,
            "read_mode": 1,
            "have_resource": 1,
            "have_comic_review": 1,
            "comic_score": 9.4,
            "review_count": "153"
          },
          {
            "id": 41737,
            "name": "魔道祖师同人专区\t",
            "cover_img": "http://image.zhuizhuiimg.com//image/2522121_1466239560.jpg",
            "finished": 0,
            "last_volume": "(薛洋)信你by雾宝QWQ",
            "topic_count": 306,
            "read_mode": 0,
            "have_resource": 1,
            "have_comic_review": 1,
            "comic_score": 9.7,
            "review_count": "209"
          },
          {
            "id": 40560,
            "name": "剑网三同人专区",
            "cover_img": "http://image.zhuizhuiimg.com//image/889286_1448018372.jpg",
            "finished": 0,
            "last_volume": "牵丝戏by桃花榴火",
            "topic_count": 720,
            "read_mode": 1,
            "have_resource": 1,
            "have_comic_review": 1,
            "comic_score": 9.5,
            "review_count": "45"
          },
          {
            "id": 40372,
            "name": "VOCALOID专区",
            "cover_img": "http://image.zhuizhuiimg.com//image/656889_1444634123.jpg",
            "finished": 0,
            "last_volume": "1卷",
            "topic_count": 539,
            "read_mode": 0,
            "have_resource": 1,
            "have_comic_review": 1,
            "comic_score": 9.3,
            "review_count": "34"
          }
        ],
        "obj_type": 2
      }
    ]
  },
  "sort": {
    "errorCode": 0,
    "themes": [
      {
        "id": 43,
        "name": "最近更新",
        "cover": "http://image.zhuizhuiimg.com//image/1659759_1456121318.jpg",
        "type": "0",
        "need_login": 0,
        "theme_id": 39,
        "theme_info": {
          "id": 39,
          "cover": "",
          "name": "最近更新",
          "url": "zzComic://L.CL.com/39/S",
          "title": "",
          "comment_count": 0,
          "up_count": 0,
          "can_filter": 0
        }
      },
      {
        "id": 44,
        "name": "排行榜",
        "cover": "http://image.zhuizhuiimg.com//image/1659761_1456121335.jpg",
        "type": "0",
        "need_login": 0,
        "theme_id": 38,
        "theme_info": {
          "id": 38,
          "cover": "",
          "name": "排行榜",
          "url": "zzComic://R.CL.com/38/S",
          "title": "",
          "comment_count": 0,
          "up_count": 0,
          "can_filter": 0
        }
      },
      {
        "id": 45,
        "name": "已完结",
        "cover": "http://image.zhuizhuiimg.com//image/1659762_1456121348.jpg",
        "type": "0",
        "need_login": 0,
        "theme_id": 116,
        "theme_info": {
          "id": 116,
          "name": "已完结",
          "url": "zzComic://L.CL.com/116/S",
          "title": "",
          "comment_count": 0,
          "up_count": 0,
          "can_filter": 0
        }
      },
      {
        "id": 62,
        "name": "最新收录",
        "cover": "http://image.zhuizhuiimg.com//image/1659945_1456122309.jpg",
        "type": "0",
        "need_login": 0,
        "theme_id": 1047,
        "theme_info": {
          "id": 1047,
          "cover": "",
          "name": "最新收录",
          "url": "zzComic://L.CL.com/1047/S",
          "title": "",
          "comment_count": 0,
          "up_count": 0,
          "can_filter": 0
        }
      },
      {
        "id": 63,
        "name": "周五の下午茶",
        "cover": "http://image.zhuizhuiimg.com//image/1659949_1456122320.jpg",
        "type": "0",
        "need_login": 0,
        "theme_id": 3415,
        "theme_info": {
          "id": 3415,
          "cover": "http://image.zhuizhuiimg.com//image/721034_1445596556.jpg",
          "name": "【往期回顾】周五の下午茶",
          "url": "http://aizhuizhui.com/afternoon_tea",
          "comment_count": 0,
          "up_count": 0,
          "can_filter": 0
        }
      },
      {
        "id": 65,
        "name": "漫画专辑",
        "cover": "http://image.zhuizhuiimg.com//image/1659955_1456122340.jpg",
        "type": "0",
        "need_login": 0,
        "theme_id": 1712,
        "theme_info": {
          "id": 1712,
          "cover": "",
          "name": "全部专辑",
          "url": "zzComic://CTLS.com/1712/L",
          "title": "优质专辑展示区",
          "comment_count": 0,
          "up_count": 0,
          "can_filter": 0
        }
      },
      {
        "id": 61,
        "name": "调戏追追娘",
        "cover": "http://image.zhuizhuiimg.com//image/1675402_1456297967.jpg",
        "type": "0",
        "need_login": 0,
        "theme_id": 1011,
        "theme_info": {
          "id": 1011,
          "cover": "http://image.zhuizhuiimg.com//image/33653_1429516788.jpg",
          "name": "追追娘的微信",
          "url": "http://aizhuizhui.com/new/2898",
          "comment_count": 0,
          "up_count": 0,
          "can_filter": 0
        }
      },
      {
        "id": 16,
        "name": "国漫",
        "cover": "http://image.zhuizhuiimg.com//image/1675303_1456297065.jpg",
        "type": "0",
        "need_login": 0,
        "theme_id": 44,
        "theme_info": {
          "id": 44,
          "cover": "",
          "name": "国漫",
          "url": "zzComic://G.CL.com/44",
          "title": "",
          "comment_count": 0,
          "up_count": 0,
          "can_filter": 1
        }
      },
      {
        "id": 17,
        "name": "日漫",
        "cover": "http://image.zhuizhuiimg.com//image/1675300_1456297007.jpg",
        "type": "0",
        "need_login": 0,
        "theme_id": 45,
        "theme_info": {
          "id": 45,
          "cover": "",
          "name": "日漫",
          "url": "zzComic://G.CL.com/45",
          "title": "",
          "comment_count": 0,
          "up_count": 0,
          "can_filter": 1
        }
      },
      {
        "id": 21,
        "name": "欧美",
        "cover": "http://image.zhuizhuiimg.com//image/1659977_1456122420.jpg",
        "type": "0",
        "need_login": 0,
        "theme_id": 46,
        "theme_info": {
          "id": 46,
          "cover": "",
          "name": "欧美",
          "url": "zzComic://G.CL.com/46",
          "title": "",
          "comment_count": 0,
          "up_count": 0,
          "can_filter": 1
        }
      },
      {
        "id": 66,
        "name": "别点我",
        "cover": "http://image.zhuizhuiimg.com//image/1659981_1456122440.jpg",
        "type": "0",
        "need_login": 0,
        "theme_id": 5529,
        "theme_info": {
          "id": 5529,
          "cover": "http://image.zhuizhuiimg.com//image/3289696_1476342138.jpg",
          "name": "追追娘私藏的游戏",
          "url": "zzcomic://G.center.com",
          "comment_count": 0,
          "up_count": 0,
          "can_filter": 0
        }
      },
      {
        "id": 22,
        "name": "韩漫",
        "cover": "http://image.zhuizhuiimg.com//image/1662699_1456139672.jpg",
        "type": "0",
        "need_login": 0,
        "theme_id": 94,
        "theme_info": {
          "id": 94,
          "cover": "",
          "name": "韩漫",
          "url": "zzComic://G.CL.com/94",
          "title": "",
          "comment_count": 0,
          "up_count": 0,
          "can_filter": 1
        }
      },
      {
        "id": 20,
        "name": "港台",
        "cover": "http://image.zhuizhuiimg.com//image/1659993_1456122485.jpg",
        "type": "0",
        "need_login": 0,
        "theme_id": 47,
        "theme_info": {
          "id": 47,
          "cover": "",
          "name": "港台",
          "url": "zzComic://G.CL.com/47",
          "title": "",
          "comment_count": 0,
          "up_count": 0,
          "can_filter": 1
        }
      },
      {
        "id": 24,
        "name": "少年热血",
        "cover": "http://image.zhuizhuiimg.com//image/1676299_1456307272.jpg",
        "type": "0",
        "need_login": 0,
        "theme_id": 62,
        "theme_info": {
          "id": 62,
          "cover": "",
          "name": "少年热血",
          "url": "zzComic://G.CL.com/62",
          "title": "",
          "comment_count": 0,
          "up_count": 0,
          "can_filter": 1
        }
      },
      {
        "id": 25,
        "name": "少女爱情",
        "cover": "http://image.zhuizhuiimg.com//image/1660016_1456122551.jpg",
        "type": "0",
        "need_login": 0,
        "theme_id": 63,
        "theme_info": {
          "id": 63,
          "cover": "",
          "name": "少女爱情",
          "url": "zzComic://G.CL.com/63",
          "title": "",
          "comment_count": 0,
          "up_count": 0,
          "can_filter": 1
        }
      },
      {
        "id": 26,
        "name": "冒险",
        "cover": "http://image.zhuizhuiimg.com//image/1662704_1456139717.jpg",
        "type": "0",
        "need_login": 0,
        "theme_id": 61,
        "theme_info": {
          "id": 61,
          "cover": "",
          "name": "冒险",
          "url": "zzComic://G.CL.com/61",
          "title": "",
          "comment_count": 0,
          "up_count": 0,
          "can_filter": 1
        }
      },
      {
        "id": 27,
        "name": "搞笑",
        "cover": "http://image.zhuizhuiimg.com//image/1660031_1456122590.jpg",
        "type": "0",
        "need_login": 0,
        "theme_id": 64,
        "theme_info": {
          "id": 64,
          "cover": "",
          "name": "搞笑",
          "url": "zzComic://G.CL.com/64",
          "title": "",
          "comment_count": 0,
          "up_count": 0,
          "can_filter": 1
        }
      },
      {
        "id": 28,
        "name": "治愈",
        "cover": "http://image.zhuizhuiimg.com//image/1660036_1456122605.jpg",
        "type": "0",
        "need_login": 0,
        "theme_id": 66,
        "theme_info": {
          "id": 66,
          "cover": "",
          "name": "治愈",
          "url": "zzComic://G.CL.com/66",
          "title": "",
          "comment_count": 0,
          "up_count": 0,
          "can_filter": 1
        }
      },
      {
        "id": 29,
        "name": "校园",
        "cover": "http://image.zhuizhuiimg.com//image/1675289_1456296761.jpg",
        "type": "0",
        "need_login": 0,
        "theme_id": 74,
        "theme_info": {
          "id": 74,
          "cover": "",
          "name": "校园",
          "url": "zzComic://G.CL.com/74",
          "title": "",
          "comment_count": 0,
          "up_count": 0,
          "can_filter": 1
        }
      },
      {
        "id": 30,
        "name": "魔法",
        "cover": "http://image.zhuizhuiimg.com//image/1660047_1456122644.jpg",
        "type": "0",
        "need_login": 0,
        "theme_id": 65,
        "theme_info": {
          "id": 65,
          "cover": "",
          "name": "魔法",
          "url": "zzComic://G.CL.com/65",
          "title": "",
          "comment_count": 0,
          "up_count": 0,
          "can_filter": 1
        }
      },
      {
        "id": 31,
        "name": "轻小说",
        "cover": "http://image.zhuizhuiimg.com//image/1660056_1456122675.jpg",
        "type": "0",
        "need_login": 0,
        "theme_id": 70,
        "theme_info": {
          "id": 70,
          "cover": "",
          "name": "轻小说",
          "url": "zzComic://G.CL.com/70",
          "title": "",
          "comment_count": 0,
          "up_count": 0,
          "can_filter": 1
        }
      },
      {
        "id": 32,
        "name": "后宫",
        "cover": "http://image.zhuizhuiimg.com//image/1660063_1456122693.jpg",
        "type": "0",
        "need_login": 0,
        "theme_id": 75,
        "theme_info": {
          "id": 75,
          "cover": "",
          "name": "后宫",
          "url": "zzComic://G.CL.com/75",
          "title": "",
          "comment_count": 0,
          "up_count": 0,
          "can_filter": 1
        }
      },
      {
        "id": 33,
        "name": "伪娘",
        "cover": "http://image.zhuizhuiimg.com//image/1660068_1456122708.jpg",
        "type": "0",
        "need_login": 0,
        "theme_id": 76,
        "theme_info": {
          "id": 76,
          "cover": "",
          "name": "伪娘",
          "url": "zzComic://G.CL.com/76",
          "title": "",
          "comment_count": 0,
          "up_count": 0,
          "can_filter": 1
        }
      },
      {
        "id": 34,
        "name": "百合",
        "cover": "http://image.zhuizhuiimg.com//image/1675292_1456296789.jpg",
        "type": "0",
        "need_login": 1,
        "theme_id": 73,
        "theme_info": {
          "id": 73,
          "cover": "",
          "name": "百合",
          "url": "zzComic://G.CL.com/73",
          "title": "",
          "comment_count": 0,
          "up_count": 0,
          "can_filter": 1
        }
      },
      {
        "id": 35,
        "name": "耽美",
        "cover": "http://image.zhuizhuiimg.com//image/1660084_1456122775.jpg",
        "type": "0",
        "need_login": 1,
        "theme_id": 72,
        "theme_info": {
          "id": 72,
          "cover": "",
          "name": "耽美",
          "url": "zzComic://G.CL.com/72",
          "title": "",
          "comment_count": 0,
          "up_count": 0,
          "can_filter": 1
        }
      },
      {
        "id": 36,
        "name": "宅男腐女",
        "cover": "http://image.zhuizhuiimg.com//image/1660093_1456122807.jpg",
        "type": "0",
        "need_login": 1,
        "theme_id": 79,
        "theme_info": {
          "id": 79,
          "cover": "",
          "name": "宅男腐女",
          "url": "zzComic://G.CL.com/79",
          "title": "",
          "comment_count": 0,
          "up_count": 0,
          "can_filter": 1
        }
      },
      {
        "id": 39,
        "name": "奇幻",
        "cover": "http://image.zhuizhuiimg.com//image/1660098_1456122822.jpg",
        "type": "0",
        "need_login": 0,
        "theme_id": 80,
        "theme_info": {
          "id": 80,
          "cover": "",
          "name": "奇幻",
          "url": "zzComic://G.CL.com/80",
          "title": "",
          "comment_count": 0,
          "up_count": 0,
          "can_filter": 1
        }
      },
      {
        "id": 38,
        "name": "穿越",
        "cover": "http://image.zhuizhuiimg.com//image/1660103_1456122833.jpg",
        "type": "0",
        "need_login": 0,
        "theme_id": 85,
        "theme_info": {
          "id": 85,
          "cover": "",
          "name": "穿越",
          "url": "zzComic://G.CL.com/85",
          "title": "",
          "comment_count": 0,
          "up_count": 0,
          "can_filter": 1
        }
      },
      {
        "id": 37,
        "name": "历史",
        "cover": "http://image.zhuizhuiimg.com//image/1660106_1456122848.jpg",
        "type": "0",
        "need_login": 0,
        "theme_id": 86,
        "theme_info": {
          "id": 86,
          "cover": "",
          "name": "历史",
          "url": "zzComic://G.CL.com/86",
          "title": "",
          "comment_count": 0,
          "up_count": 0,
          "can_filter": 1
        }
      },
      {
        "id": 40,
        "name": "推理",
        "cover": "http://image.zhuizhuiimg.com//image/1660109_1456122861.jpg",
        "type": "0",
        "need_login": 0,
        "theme_id": 82,
        "theme_info": {
          "id": 82,
          "cover": "",
          "name": "推理",
          "url": "zzComic://G.CL.com/82",
          "title": "",
          "comment_count": 0,
          "up_count": 0,
          "can_filter": 1
        }
      },
      {
        "id": 42,
        "name": "悬疑",
        "cover": "http://image.zhuizhuiimg.com//image/1660110_1456122873.jpg",
        "type": "0",
        "need_login": 0,
        "theme_id": 83,
        "theme_info": {
          "id": 83,
          "cover": "",
          "name": "悬疑",
          "url": "zzComic://G.CL.com/83",
          "title": "",
          "comment_count": 0,
          "up_count": 0,
          "can_filter": 1
        }
      },
      {
        "id": 46,
        "name": "科幻",
        "cover": "http://image.zhuizhuiimg.com//image/1675293_1456296814.jpg",
        "type": "0",
        "need_login": 0,
        "theme_id": 84,
        "theme_info": {
          "id": 84,
          "cover": "",
          "name": "科幻",
          "url": "zzComic://G.CL.com/84",
          "title": "",
          "comment_count": 0,
          "up_count": 0,
          "can_filter": 1
        }
      },
      {
        "id": 47,
        "name": "机战",
        "cover": "http://image.zhuizhuiimg.com//image/1660114_1456122923.jpg",
        "type": "0",
        "need_login": 0,
        "theme_id": 87,
        "theme_info": {
          "id": 87,
          "cover": "",
          "name": "机战",
          "url": "zzComic://G.CL.com/87",
          "title": "",
          "comment_count": 0,
          "up_count": 0,
          "can_filter": 1
        }
      },
      {
        "id": 48,
        "name": "竞技",
        "cover": "http://image.zhuizhuiimg.com//image/1660115_1456122938.jpg",
        "type": "0",
        "need_login": 0,
        "theme_id": 71,
        "theme_info": {
          "id": 71,
          "cover": "",
          "name": "竞技",
          "url": "zzComic://G.CL.com/71",
          "title": "",
          "comment_count": 0,
          "up_count": 0,
          "can_filter": 1
        }
      },
      {
        "id": 49,
        "name": "东方",
        "cover": "http://image.zhuizhuiimg.com//image/1660118_1456122952.jpg",
        "type": "0",
        "need_login": 0,
        "theme_id": 78,
        "theme_info": {
          "id": 78,
          "cover": "",
          "name": "东方",
          "url": "zzComic://G.CL.com/78",
          "title": "",
          "comment_count": 0,
          "up_count": 0,
          "can_filter": 1
        }
      },
      {
        "id": 50,
        "name": "同人",
        "cover": "http://image.zhuizhuiimg.com//image/1662715_1456139819.jpg",
        "type": "0",
        "need_login": 1,
        "theme_id": 77,
        "theme_info": {
          "id": 77,
          "cover": "",
          "name": "同人",
          "url": "zzComic://G.CL.com/77",
          "title": "",
          "comment_count": 0,
          "up_count": 0,
          "can_filter": 1
        }
      },
      {
        "id": 51,
        "name": "音乐舞蹈",
        "cover": "http://image.zhuizhuiimg.com//image/1662709_1456139785.jpg",
        "type": "0",
        "need_login": 0,
        "theme_id": 88,
        "theme_info": {
          "id": 88,
          "cover": "",
          "name": "音乐舞蹈",
          "url": "zzComic://G.CL.com/88",
          "title": "",
          "comment_count": 0,
          "up_count": 0,
          "can_filter": 1
        }
      },
      {
        "id": 54,
        "name": "生活",
        "cover": "http://image.zhuizhuiimg.com//image/1675295_1456296888.jpg",
        "type": "0",
        "need_login": 0,
        "theme_id": 69,
        "theme_info": {
          "id": 69,
          "cover": "",
          "name": "生活",
          "url": "zzComic://G.CL.com/69",
          "title": "",
          "comment_count": 0,
          "up_count": 0,
          "can_filter": 1
        }
      },
      {
        "id": 52,
        "name": "美食",
        "cover": "http://image.zhuizhuiimg.com//image/1676300_1456307297.jpg",
        "type": "0",
        "need_login": 0,
        "theme_id": 90,
        "theme_info": {
          "id": 90,
          "cover": "",
          "name": "美食",
          "url": "zzComic://G.CL.com/90",
          "title": "",
          "comment_count": 0,
          "up_count": 0,
          "can_filter": 1
        }
      },
      {
        "id": 53,
        "name": "职场",
        "cover": "http://image.zhuizhuiimg.com//image/1660141_1456123015.jpg",
        "type": "0",
        "need_login": 0,
        "theme_id": 89,
        "theme_info": {
          "id": 89,
          "cover": "",
          "name": "职场",
          "url": "zzComic://G.CL.com/89",
          "title": "",
          "comment_count": 0,
          "up_count": 0,
          "can_filter": 1
        }
      },
      {
        "id": 55,
        "name": "西方魔幻",
        "cover": "http://image.zhuizhuiimg.com//image/1660145_1456123035.jpg",
        "type": "0",
        "need_login": 0,
        "theme_id": 49,
        "theme_info": {
          "id": 49,
          "cover": "",
          "name": "西方魔幻",
          "url": "zzComic://G.CL.com/49",
          "title": "",
          "comment_count": 0,
          "up_count": 0,
          "can_filter": 1
        }
      },
      {
        "id": 56,
        "name": "东方神鬼",
        "cover": "http://image.zhuizhuiimg.com//image/1676302_1456307314.jpg",
        "type": "0",
        "need_login": 0,
        "theme_id": 93,
        "theme_info": {
          "id": 93,
          "cover": "",
          "name": "东方神鬼",
          "url": "zzComic://G.CL.com/93",
          "title": "",
          "comment_count": 0,
          "up_count": 0,
          "can_filter": 1
        }
      },
      {
        "id": 57,
        "name": "格斗武侠",
        "cover": "http://image.zhuizhuiimg.com//image/1676307_1456307331.jpg",
        "type": "0",
        "need_login": 0,
        "theme_id": 68,
        "theme_info": {
          "id": 68,
          "cover": "",
          "name": "格斗武侠",
          "url": "zzComic://G.CL.com/68",
          "title": "",
          "comment_count": 0,
          "up_count": 0,
          "can_filter": 1
        }
      },
      {
        "id": 58,
        "name": "萌系",
        "cover": "http://image.zhuizhuiimg.com//image/1660161_1456123095.jpg",
        "type": "0",
        "need_login": 0,
        "theme_id": 91,
        "theme_info": {
          "id": 91,
          "cover": "",
          "name": "萌系",
          "url": "zzComic://G.CL.com/91",
          "title": "",
          "comment_count": 0,
          "up_count": 0,
          "can_filter": 1
        }
      },
      {
        "id": 59,
        "name": "四格",
        "cover": "http://image.zhuizhuiimg.com//image/1660164_1456123108.jpg",
        "type": "0",
        "need_login": 0,
        "theme_id": 92,
        "theme_info": {
          "id": 92,
          "cover": "",
          "name": "四格",
          "url": "zzComic://G.CL.com/92",
          "title": "",
          "comment_count": 0,
          "up_count": 0,
          "can_filter": 1
        }
      }
    ],
    "keywords": [],
    "banner_total": "4",
    "banners": [
      {
        "id": "6",
        "cover": "http://image.zhuizhuiimg.com//image/3066358_1471439678.jpg",
        "title": "图区",
        "url": "zzcomic://W.com",
        "rank": "1"
      },
      {
        "id": "4",
        "cover": "http://image.zhuizhuiimg.com//image/3009768_1470903984.jpg",
        "title": "",
        "url": "zzComic://L.TL.com/3900",
        "rank": "0"
      },
      {
        "id": "3",
        "cover": "http://image.zhuizhuiimg.com//image/3009767_1470903973.jpg",
        "title": "",
        "url": "zzComic://mpb.com",
        "rank": "0"
      },
      {
        "id": "2",
        "cover": "http://image.zhuizhuiimg.com//image/3009766_1470903961.jpg",
        "title": "",
        "url": "http://aizhuizhui.com/new/58233",
        "rank": "0"
      }
    ]
  }
}
